nonebot/adapters/console/__init__.py
nonebot/adapters/console/adapter.py
nonebot/adapters/console/backend.py
nonebot/adapters/console/bot.py
nonebot/adapters/console/config.py
nonebot/adapters/console/event.py
nonebot/adapters/console/exception.py
nonebot/adapters/console/message.py
nonebot/adapters/console/utils.py
nonebot_adapter_console-0.9.0.dist-info/METADATA
nonebot_adapter_console-0.9.0.dist-info/WHEEL
nonebot_adapter_console-0.9.0.dist-info/entry_points.txt
nonebot_adapter_console-0.9.0.dist-info/licenses/LICENSE
nonebot_adapter_console-0.9.0.dist-info/RECORD
