Metadata-Version: 2.1
Name: nonebot-adapter-console
Version: 0.9.0
Summary: console adapter for nonebot2
Author-Email: RF-Tar-Railt <rf_tar_railt@qq.com>, MelodyKnit <yanximelody@gmail.com>, yanyongyu <yyy@nonebot.dev>
License: MIT
Requires-Python: <4.0,>=3.9
Requires-Dist: nonechat<0.7.0,>=0.6.0
Requires-Dist: nonebot2>=2.4.2
Requires-Dist: typing-extensions>=4.7.1
